fifo.v
`timescale 1ns/1ps

module fifo (
    input clk,
    input rst,
    input wr_en,
    input rd_en,
    input [7:0] din,
    output reg [7:0] dout,
    output reg full,
    output reg empty
);

reg [7:0] mem [0:3];
reg [1:0] wptr, rptr;
reg [2:0] count;

always @(posedge clk or posedge rst) begin
    if (rst) begin
        wptr  <= 0;
        rptr  <= 0;
        count <= 0;
        full  <= 0;
        empty <= 1;
        dout  <= 0;
    end
    else begin
        if (wr_en && !full) begin
            mem[wptr] <= din;
            wptr <= wptr + 1;
            count <= count + 1;
        end

        if (rd_en && !empty) begin
            dout <= mem[rptr];
            rptr <= rptr + 1;
            count <= count - 1;
        end

        full  <= (count == 4);
        empty <= (count == 0);
    end
end

endmodule

tb.v
`timescale 1ns/1ps

module tb;

reg clk;
reg rst;
reg wr_en;
reg rd_en;
reg [7:0] din;
wire [7:0] dout;
wire full;
wire empty;

fifo dut (
    .clk(clk),
    .rst(rst),
    .wr_en(wr_en),
    .rd_en(rd_en),
    .din(din),
    .dout(dout),
    .full(full),
    .empty(empty)
);

always #5 clk = ~clk;

initial begin
    $dumpfile("fifo.vcd");
    $dumpvars(0,tb);

    clk   = 0;
    rst   = 1;
    wr_en = 0;
    rd_en = 0;
    din   = 0;

    #10 rst = 0;

    wr_en = 1; din = 8'h11; #10;
    din = 8'h22; #10;
    din = 8'h33; #10;
    din = 8'h44; #10;
    wr_en = 0;

    rd_en = 1; #10;
    #10;
    #10;
    #10;
    rd_en = 0;

    #20 $finish;
end

always @(posedge clk) begin
    $display("time=%0t din=%h dout=%h full=%b empty=%b",
              $time,din,dout,full,empty);
end

endmodule

fifo.vcd
$version Generated by VerilatedVcd $end
$timescale 1ps $end
 $scope module tb $end
  $var wire 1 , clk $end
  $var wire 1 - rst $end
  $var wire 1 . wr_en $end
  $var wire 1 / rd_en $end
  $var wire 8 0 din [7:0] $end
  $var wire 8 " dout [7:0] $end
  $var wire 1 # full $end
  $var wire 1 $ empty $end
  $scope module dut $end
   $var wire 1 , clk $end
   $var wire 1 - rst $end
   $var wire 1 . wr_en $end
   $var wire 1 / rd_en $end
   $var wire 8 0 din [7:0] $end
   $var wire 8 " dout [7:0] $end
   $var wire 1 # full $end
   $var wire 1 $ empty $end
   $var wire 8 % mem[0] [7:0] $end
   $var wire 8 & mem[1] [7:0] $end
   $var wire 8 ' mem[2] [7:0] $end
   $var wire 8 ( mem[3] [7:0] $end
   $var wire 2 ) wptr [1:0] $end
   $var wire 2 * rptr [1:0] $end
   $var wire 3 + count [2:0] $end
  $upscope $end
 $upscope $end
$enddefinitions $end


#0
b00000000 "
0#
1$
b00000000 %
b00000000 &
b00000000 '
b00000000 (
b00 )
b00 *
b000 +
0,
1-
0.
0/
b00000000 0
#5000
1,
#10000
0,
0-
1.
b00010001 0
#15000
b00010001 %
b01 )
b001 +
1,
#20000
0,
b00100010 0
#25000
0$
b00100010 &
b10 )
b010 +
1,
#30000
0,
b00110011 0
#35000
b00110011 '
b11 )
b011 +
1,
#40000
0,
b01000100 0
#45000
b01000100 (
b00 )
b100 +
1,
#50000
0,
0.
1/
#55000
b00010001 "
1#
b01 *
b011 +
1,
#60000
0,
#65000
b00100010 "
0#
b10 *
b010 +
1,
#70000
0,
#75000
b00110011 "
b11 *
b001 +
1,
#80000
0,
#85000
b01000100 "
b00 *
b000 +
1,
#90000
0,
0/
#95000
1$
1,
